decolle/__init__.py
decolle/allconv_decolle.py
decolle/base_model.py
decolle/init_functions.py
decolle/lenet_decolle_model.py
decolle/lenet_decolle_model_errortriggered.py
decolle/lenet_decolle_model_fa.py
decolle/lenet_delle.py
decolle/lenet_redecolle.py
decolle/snn_utils.py
decolle/utils.py
decolle/experimental/__init__.py
decolle/experimental/boxlif.py
decolle-0.2.dist-info/LICENSE.txt
decolle-0.2.dist-info/METADATA
decolle-0.2.dist-info/WHEEL
decolle-0.2.dist-info/top_level.txt
decolle-0.2.dist-info/RECORD
