Metadata-Version: 2.1
Name: decolle
Version: 0.2
Summary: Deep Continuous Local Learning
Author: Emre Neftci, Massi Iacono, Jacques Kaiser
Author-email: eneftci@uci.edu
License: GPL 3.0
Keywords: spiking neural networks learning
Platform: UNKNOWN
License-File: LICENSE.txt
Requires-Dist: torch (>=0.4)
Requires-Dist: scipy (>=1.0)
Requires-Dist: h5py
Requires-Dist: tqdm
Requires-Dist: tensorboardX
Requires-Dist: torchneuromorphic
Requires-Dist: pyyaml
